{
  "close_df": [
    {
      "date": "2026-03-10",
      "microcap": 1033.0026929604996,
      "hedge": 8350.09
    },
    {
      "date": "2026-03-11",
      "microcap": 1026.1759395303704,
      "hedge": 8363.53
    },
    {
      "date": "2026-03-12",
      "microcap": 1011.3563674475083,
      "hedge": 8335.91
    },
    {
      "date": "2026-03-13",
      "microcap": 1012.1379964775955,
      "hedge": 8214.29
    },
    {
      "date": "2026-03-16",
      "microcap": 1008.8441269285314,
      "hedge": 8211.35
    },
    {
      "date": "2026-03-17",
      "microcap": 984.0966691549829,
      "hedge": 8019.86
    },
    {
      "date": "2026-03-18",
      "microcap": 1004.751857810327,
      "hedge": 8096.59
    },
    {
      "date": "2026-03-19",
      "microcap": 974.6895651548508,
      "hedge": 7909.23
    },
    {
      "date": "2026-03-20",
      "microcap": 933.3232036947464,
      "hedge": 7783.43
    },
    {
      "date": "2026-03-23",
      "microcap": 874.4191008949578,
      "hedge": 7409.11
    },
    {
      "date": "2026-03-24",
      "microcap": 931.7648611018835,
      "hedge": 7600.86
    },
    {
      "date": "2026-03-25",
      "microcap": 958.1417746371185,
      "hedge": 7751.18
    },
    {
      "date": "2026-03-26",
      "microcap": 941.5030289213137,
      "hedge": 7639.38
    },
    {
      "date": "2026-03-27",
      "microcap": 959.1862373597305,
      "hedge": 7746.31
    },
    {
      "date": "2026-03-30",
      "microcap": 970.1912502888505,
      "hedge": 7767.93
    },
    {
      "date": "2026-03-31",
      "microcap": 955.1275695704414,
      "hedge": 7619.85
    },
    {
      "date": "2026-04-01",
      "microcap": 961.5497761177145,
      "hedge": 7764.15
    },
    {
      "date": "2026-04-02",
      "microcap": 934.7899957992394,
      "hedge": 7623.42
    },
    {
      "date": "2026-04-03",
      "microcap": 896.7403726103521,
      "hedge": 7536.6
    },
    {
      "date": "2026-04-07",
      "microcap": 926.5487298165887,
      "hedge": 7606.02
    },
    {
      "date": "2026-04-08",
      "microcap": 968.4032833690671,
      "hedge": 7955.77
    },
    {
      "date": "2026-04-09",
      "microcap": 941.6208463579686,
      "hedge": 7921.45
    },
    {
      "date": "2026-04-10",
      "microcap": 952.610033107432,
      "hedge": 7998.23
    }
  ],
  "latest_signal": [
    {
      "date": "2026-04-10",
      "signal_label": "cash",
      "next_holding": "cash",
      "microcap_close": 952.610033107432,
      "hedge_close": 7998.23,
      "microcap_mom": -0.051895225968060066,
      "hedge_mom": -0.012148324171039948,
      "momentum_gap": -0.03974690179702012,
      "ratio_bias_mom": NaN,
      "ratio_r2": 0.07877898382136951,
      "hedge_ratio": 0.8,
      "weight": 1.0,
      "futures_drag": 0.0,
      "current_holding": "cash",
      "trade_state": "hold",
      "momentum_trade_state": "hold",
      "member_rebalance_state": "rebalance",
      "member_rebalance_required": true,
      "member_enter_count": 10,
      "member_exit_count": 10,
      "member_rebalance_label": "名单调仓（调入 10，调出 10）"
    }
  ],
  "target_members": [
    {
      "rebalance_date": "2026-04-02",
      "rank": 1,
      "symbol": "688701",
      "name": "卓锦股份",
      "market_cap": 1220581311.48,
      "target_weight": 0.01,
      "signal_date": "2026-04-02",
      "effective_date": "2026-04-03"
    },
    {
      "rebalance_date": "2026-04-02",
      "rank": 2,
      "symbol": "688296",
      "name": "和达科技",
      "market_cap": 1462026843.0,
      "target_weight": 0.01,
      "signal_date": "2026-04-02",
      "effective_date": "2026-04-03"
    },
    {
      "rebalance_date": "2026-04-02",
      "rank": 3,
      "symbol": "002193",
      "name": "如意集团",
      "market_cap": 1481310013.0,
      "target_weight": 0.01,
      "signal_date": "2026-04-02",
      "effective_date": "2026-04-03"
    },
    {
      "rebalance_date": "2026-04-02",
      "rank": 4,
      "symbol": "002856",
      "name": "美芝股份",
      "market_cap": 1481675247.6,
      "target_weight": 0.01,
      "signal_date": "2026-04-02",
      "effective_date": "2026-04-03"
    },
    {
      "rebalance_date": "2026-04-02",
      "rank": 5,
      "symbol": "002883",
      "name": "中设股份",
      "market_cap": 1481931505.3400002,
      "target_weight": 0.01,
      "signal_date": "2026-04-02",
      "effective_date": "2026-04-03"
    },
    {
      "rebalance_date": "2026-04-02",
      "rank": 6,
      "symbol": "002719",
      "name": "麦趣尔",
      "market_cap": 1483668173.6399999,
      "target_weight": 0.01,
      "signal_date": "2026-04-02",
      "effective_date": "2026-04-03"
    },
    {
      "rebalance_date": "2026-04-02",
      "rank": 7,
      "symbol": "688659",
      "name": "元琛科技",
      "market_cap": 1534400000.0,
      "target_weight": 0.01,
      "signal_date": "2026-04-02",
      "effective_date": "2026-04-03"
    },
    {
      "rebalance_date": "2026-04-02",
      "rank": 8,
      "symbol": "301098",
      "name": "金埔园林",
      "market_cap": 1535862084.65,
      "target_weight": 0.01,
      "signal_date": "2026-04-02",
      "effective_date": "2026-04-03"
    },
    {
      "rebalance_date": "2026-04-02",
      "rank": 9,
      "symbol": "600543",
      "name": "莫高股份",
      "market_cap": 1538164800.0,
      "target_weight": 0.01,
      "signal_date": "2026-04-02",
      "effective_date": "2026-04-03"
    },
    {
      "rebalance_date": "2026-04-02",
      "rank": 10,
      "symbol": "603729",
      "name": "龙韵股份",
      "market_cap": 1568078400.0,
      "target_weight": 0.01,
      "signal_date": "2026-04-02",
      "effective_date": "2026-04-03"
    },
    {
      "rebalance_date": "2026-04-02",
      "rank": 11,
      "symbol": "688217",
      "name": "睿昂基因",
      "market_cap": 1571784913.44,
      "target_weight": 0.01,
      "signal_date": "2026-04-02",
      "effective_date": "2026-04-03"
    },
    {
      "rebalance_date": "2026-04-02",
      "rank": 12,
      "symbol": "600455",
      "name": "博通股份",
      "market_cap": 1618286780.0000002,
      "target_weight": 0.01,
      "signal_date": "2026-04-02",
      "effective_date": "2026-04-03"
    },
    {
      "rebalance_date": "2026-04-02",
      "rank": 13,
      "symbol": "300417",
      "name": "南华仪器",
      "market_cap": 1637634144.0,
      "target_weight": 0.01,
      "signal_date": "2026-04-02",
      "effective_date": "2026-04-03"
    },
    {
      "rebalance_date": "2026-04-02",
      "rank": 14,
      "symbol": "300929",
      "name": "华骐环保",
      "market_cap": 1643733972.64,
      "target_weight": 0.01,
      "signal_date": "2026-04-02",
      "effective_date": "2026-04-03"
    },
    {
      "rebalance_date": "2026-04-02",
      "rank": 15,
      "symbol": "300665",
      "name": "飞鹿股份",
      "market_cap": 1646471889.6,
      "target_weight": 0.01,
      "signal_date": "2026-04-02",
      "effective_date": "2026-04-03"
    },
    {
      "rebalance_date": "2026-04-02",
      "rank": 16,
      "symbol": "300621",
      "name": "维业股份",
      "market_cap": 1666534166.9999998,
      "target_weight": 0.01,
      "signal_date": "2026-04-02",
      "effective_date": "2026-04-03"
    },
    {
      "rebalance_date": "2026-04-02",
      "rank": 17,
      "symbol": "688671",
      "name": "碧兴物联",
      "market_cap": 1678734082.0,
      "target_weight": 0.01,
      "signal_date": "2026-04-02",
      "effective_date": "2026-04-03"
    },
    {
      "rebalance_date": "2026-04-02",
      "rank": 18,
      "symbol": "688004",
      "name": "博汇科技",
      "market_cap": 1709077920.0000002,
      "target_weight": 0.01,
      "signal_date": "2026-04-02",
      "effective_date": "2026-04-03"
    },
    {
      "rebalance_date": "2026-04-02",
      "rank": 19,
      "symbol": "600476",
      "name": "湘邮科技",
      "market_cap": 1720227600.0,
      "target_weight": 0.01,
      "signal_date": "2026-04-02",
      "effective_date": "2026-04-03"
    },
    {
      "rebalance_date": "2026-04-02",
      "rank": 20,
      "symbol": "688078",
      "name": "龙软科技",
      "market_cap": 1755263439.9999998,
      "target_weight": 0.01,
      "signal_date": "2026-04-02",
      "effective_date": "2026-04-03"
    },
    {
      "rebalance_date": "2026-04-02",
      "rank": 21,
      "symbol": "300405",
      "name": "科隆股份",
      "market_cap": 1763110560.2000003,
      "target_weight": 0.01,
      "signal_date": "2026-04-02",
      "effective_date": "2026-04-03"
    },
    {
      "rebalance_date": "2026-04-02",
      "rank": 22,
      "symbol": "301372",
      "name": "科净源",
      "market_cap": 1788342894.3999999,
      "target_weight": 0.01,
      "signal_date": "2026-04-02",
      "effective_date": "2026-04-03"
    },
    {
      "rebalance_date": "2026-04-02",
      "rank": 23,
      "symbol": "688528",
      "name": "秦川物联",
      "market_cap": 1795920000.0,
      "target_weight": 0.01,
      "signal_date": "2026-04-02",
      "effective_date": "2026-04-03"
    },
    {
      "rebalance_date": "2026-04-02",
      "rank": 24,
      "symbol": "688067",
      "name": "爱威科技",
      "market_cap": 1801320000.0,
      "target_weight": 0.01,
      "signal_date": "2026-04-02",
      "effective_date": "2026-04-03"
    },
    {
      "rebalance_date": "2026-04-02",
      "rank": 25,
      "symbol": "300295",
      "name": "三六五网",
      "market_cap": 1812707105.8400002,
      "target_weight": 0.01,
      "signal_date": "2026-04-02",
      "effective_date": "2026-04-03"
    },
    {
      "rebalance_date": "2026-04-02",
      "rank": 26,
      "symbol": "301167",
      "name": "建研设计",
      "market_cap": 1818879999.9999998,
      "target_weight": 0.01,
      "signal_date": "2026-04-02",
      "effective_date": "2026-04-03"
    },
    {
      "rebalance_date": "2026-04-02",
      "rank": 27,
      "symbol": "300500",
      "name": "启迪设计",
      "market_cap": 1837174616.64,
      "target_weight": 0.01,
      "signal_date": "2026-04-02",
      "effective_date": "2026-04-03"
    },
    {
      "rebalance_date": "2026-04-02",
      "rank": 28,
      "symbol": "600561",
      "name": "江西长运",
      "market_cap": 1849099200.0000002,
      "target_weight": 0.01,
      "signal_date": "2026-04-02",
      "effective_date": "2026-04-03"
    },
    {
      "rebalance_date": "2026-04-02",
      "rank": 29,
      "symbol": "688573",
      "name": "信宇人",
      "market_cap": 1851468108.72,
      "target_weight": 0.01,
      "signal_date": "2026-04-02",
      "effective_date": "2026-04-03"
    },
    {
      "rebalance_date": "2026-04-02",
      "rank": 30,
      "symbol": "688329",
      "name": "艾隆科技",
      "market_cap": 1853572000.0,
      "target_weight": 0.01,
      "signal_date": "2026-04-02",
      "effective_date": "2026-04-03"
    },
    {
      "rebalance_date": "2026-04-02",
      "rank": 31,
      "symbol": "300649",
      "name": "杭州园林",
      "market_cap": 1863101688.6300004,
      "target_weight": 0.01,
      "signal_date": "2026-04-02",
      "effective_date": "2026-04-03"
    },
    {
      "rebalance_date": "2026-04-02",
      "rank": 32,
      "symbol": "688021",
      "name": "奥福科技",
      "market_cap": 1872136066.5,
      "target_weight": 0.01,
      "signal_date": "2026-04-02",
      "effective_date": "2026-04-03"
    },
    {
      "rebalance_date": "2026-04-02",
      "rank": 33,
      "symbol": "600697",
      "name": "欧亚集团",
      "market_cap": 1894738973.25,
      "target_weight": 0.01,
      "signal_date": "2026-04-02",
      "effective_date": "2026-04-03"
    },
    {
      "rebalance_date": "2026-04-02",
      "rank": 34,
      "symbol": "688681",
      "name": "科汇股份",
      "market_cap": 1898713800.0,
      "target_weight": 0.01,
      "signal_date": "2026-04-02",
      "effective_date": "2026-04-03"
    },
    {
      "rebalance_date": "2026-04-02",
      "rank": 35,
      "symbol": "600883",
      "name": "博闻科技",
      "market_cap": 1905230160.0,
      "target_weight": 0.01,
      "signal_date": "2026-04-02",
      "effective_date": "2026-04-03"
    },
    {
      "rebalance_date": "2026-04-02",
      "rank": 36,
      "symbol": "688096",
      "name": "京源环保",
      "market_cap": 1907238784.32,
      "target_weight": 0.01,
      "signal_date": "2026-04-02",
      "effective_date": "2026-04-03"
    },
    {
      "rebalance_date": "2026-04-02",
      "rank": 37,
      "symbol": "300635",
      "name": "中达安",
      "market_cap": 1913991380.0,
      "target_weight": 0.01,
      "signal_date": "2026-04-02",
      "effective_date": "2026-04-03"
    },
    {
      "rebalance_date": "2026-04-02",
      "rank": 38,
      "symbol": "688565",
      "name": "力源科技",
      "market_cap": 1927025099.9999998,
      "target_weight": 0.01,
      "signal_date": "2026-04-02",
      "effective_date": "2026-04-03"
    },
    {
      "rebalance_date": "2026-04-02",
      "rank": 39,
      "symbol": "600847",
      "name": "万里股份",
      "market_cap": 1929888365.9999998,
      "target_weight": 0.01,
      "signal_date": "2026-04-02",
      "effective_date": "2026-04-03"
    },
    {
      "rebalance_date": "2026-04-02",
      "rank": 40,
      "symbol": "300169",
      "name": "天晟新材",
      "market_cap": 1936346979.6000001,
      "target_weight": 0.01,
      "signal_date": "2026-04-02",
      "effective_date": "2026-04-03"
    },
    {
      "rebalance_date": "2026-04-02",
      "rank": 41,
      "symbol": "300670",
      "name": "大烨智能",
      "market_cap": 1945891741.06,
      "target_weight": 0.01,
      "signal_date": "2026-04-02",
      "effective_date": "2026-04-03"
    },
    {
      "rebalance_date": "2026-04-02",
      "rank": 42,
      "symbol": "603717",
      "name": "天域生物",
      "market_cap": 1946881270.3999999,
      "target_weight": 0.01,
      "signal_date": "2026-04-02",
      "effective_date": "2026-04-03"
    },
    {
      "rebalance_date": "2026-04-02",
      "rank": 43,
      "symbol": "002494",
      "name": "华斯股份",
      "market_cap": 1958242626.42,
      "target_weight": 0.01,
      "signal_date": "2026-04-02",
      "effective_date": "2026-04-03"
    },
    {
      "rebalance_date": "2026-04-02",
      "rank": 44,
      "symbol": "001211",
      "name": "双枪科技",
      "market_cap": 1958400000.0,
      "target_weight": 0.01,
      "signal_date": "2026-04-02",
      "effective_date": "2026-04-03"
    },
    {
      "rebalance_date": "2026-04-02",
      "rank": 45,
      "symbol": "600778",
      "name": "友好集团",
      "market_cap": 1959280604.0800002,
      "target_weight": 0.01,
      "signal_date": "2026-04-02",
      "effective_date": "2026-04-03"
    },
    {
      "rebalance_date": "2026-04-02",
      "rank": 46,
      "symbol": "603880",
      "name": "南卫股份",
      "market_cap": 1965485600.0,
      "target_weight": 0.01,
      "signal_date": "2026-04-02",
      "effective_date": "2026-04-03"
    },
    {
      "rebalance_date": "2026-04-02",
      "rank": 47,
      "symbol": "603879",
      "name": "永悦科技",
      "market_cap": 1965614086.8000002,
      "target_weight": 0.01,
      "signal_date": "2026-04-02",
      "effective_date": "2026-04-03"
    },
    {
      "rebalance_date": "2026-04-02",
      "rank": 48,
      "symbol": "688793",
      "name": "倍轻松",
      "market_cap": 1981901362.1399999,
      "target_weight": 0.01,
      "signal_date": "2026-04-02",
      "effective_date": "2026-04-03"
    },
    {
      "rebalance_date": "2026-04-02",
      "rank": 49,
      "symbol": "002715",
      "name": "登云股份",
      "market_cap": 1992720000.0,
      "target_weight": 0.01,
      "signal_date": "2026-04-02",
      "effective_date": "2026-04-03"
    },
    {
      "rebalance_date": "2026-04-02",
      "rank": 50,
      "symbol": "600493",
      "name": "凤竹纺织",
      "market_cap": 1993760000.0,
      "target_weight": 0.01,
      "signal_date": "2026-04-02",
      "effective_date": "2026-04-03"
    },
    {
      "rebalance_date": "2026-04-02",
      "rank": 51,
      "symbol": "301336",
      "name": "趣睡科技",
      "market_cap": 2008400000.0,
      "target_weight": 0.01,
      "signal_date": "2026-04-02",
      "effective_date": "2026-04-03"
    },
    {
      "rebalance_date": "2026-04-02",
      "rank": 52,
      "symbol": "301037",
      "name": "保立佳",
      "market_cap": 2009007862.7,
      "target_weight": 0.01,
      "signal_date": "2026-04-02",
      "effective_date": "2026-04-03"
    },
    {
      "rebalance_date": "2026-04-02",
      "rank": 53,
      "symbol": "000610",
      "name": "西安旅游",
      "market_cap": 2024194553.5500002,
      "target_weight": 0.01,
      "signal_date": "2026-04-02",
      "effective_date": "2026-04-03"
    },
    {
      "rebalance_date": "2026-04-02",
      "rank": 54,
      "symbol": "300838",
      "name": "浙江力诺",
      "market_cap": 2025517040.0,
      "target_weight": 0.01,
      "signal_date": "2026-04-02",
      "effective_date": "2026-04-03"
    },
    {
      "rebalance_date": "2026-04-02",
      "rank": 55,
      "symbol": "300535",
      "name": "达威股份",
      "market_cap": 2030166801.11,
      "target_weight": 0.01,
      "signal_date": "2026-04-02",
      "effective_date": "2026-04-03"
    },
    {
      "rebalance_date": "2026-04-02",
      "rank": 56,
      "symbol": "300958",
      "name": "建工修复",
      "market_cap": 2032873429.63,
      "target_weight": 0.01,
      "signal_date": "2026-04-02",
      "effective_date": "2026-04-03"
    },
    {
      "rebalance_date": "2026-04-02",
      "rank": 57,
      "symbol": "301049",
      "name": "超越科技",
      "market_cap": 2033044414.3799999,
      "target_weight": 0.01,
      "signal_date": "2026-04-02",
      "effective_date": "2026-04-03"
    },
    {
      "rebalance_date": "2026-04-02",
      "rank": 58,
      "symbol": "603022",
      "name": "新通联",
      "market_cap": 2038000000.0,
      "target_weight": 0.01,
      "signal_date": "2026-04-02",
      "effective_date": "2026-04-03"
    },
    {
      "rebalance_date": "2026-04-02",
      "rank": 59,
      "symbol": "688193",
      "name": "仁度生物",
      "market_cap": 2041159177.8,
      "target_weight": 0.01,
      "signal_date": "2026-04-02",
      "effective_date": "2026-04-03"
    },
    {
      "rebalance_date": "2026-04-02",
      "rank": 60,
      "symbol": "603779",
      "name": "威龙股份",
      "market_cap": 2042308937.1000001,
      "target_weight": 0.01,
      "signal_date": "2026-04-02",
      "effective_date": "2026-04-03"
    },
    {
      "rebalance_date": "2026-04-02",
      "rank": 61,
      "symbol": "002591",
      "name": "恒大高新",
      "market_cap": 2044358486.04,
      "target_weight": 0.01,
      "signal_date": "2026-04-02",
      "effective_date": "2026-04-03"
    },
    {
      "rebalance_date": "2026-04-02",
      "rank": 62,
      "symbol": "688695",
      "name": "中创股份",
      "market_cap": 2045485640.9000003,
      "target_weight": 0.01,
      "signal_date": "2026-04-02",
      "effective_date": "2026-04-03"
    },
    {
      "rebalance_date": "2026-04-02",
      "rank": 63,
      "symbol": "600448",
      "name": "华纺股份",
      "market_cap": 2053212098.12,
      "target_weight": 0.01,
      "signal_date": "2026-04-02",
      "effective_date": "2026-04-03"
    },
    {
      "rebalance_date": "2026-04-02",
      "rank": 64,
      "symbol": "002188",
      "name": "中天服务",
      "market_cap": 2054212265.9199998,
      "target_weight": 0.01,
      "signal_date": "2026-04-02",
      "effective_date": "2026-04-03"
    },
    {
      "rebalance_date": "2026-04-02",
      "rank": 65,
      "symbol": "001336",
      "name": "楚环科技",
      "market_cap": 2055150395.0000002,
      "target_weight": 0.01,
      "signal_date": "2026-04-02",
      "effective_date": "2026-04-03"
    },
    {
      "rebalance_date": "2026-04-02",
      "rank": 66,
      "symbol": "300220",
      "name": "金运激光",
      "market_cap": 2068416000.0,
      "target_weight": 0.01,
      "signal_date": "2026-04-02",
      "effective_date": "2026-04-03"
    },
    {
      "rebalance_date": "2026-04-02",
      "rank": 67,
      "symbol": "300614",
      "name": "百川畅银",
      "market_cap": 2069684759.1000001,
      "target_weight": 0.01,
      "signal_date": "2026-04-02",
      "effective_date": "2026-04-03"
    },
    {
      "rebalance_date": "2026-04-02",
      "rank": 68,
      "symbol": "300106",
      "name": "西部牧业",
      "market_cap": 2071056638.0,
      "target_weight": 0.01,
      "signal_date": "2026-04-02",
      "effective_date": "2026-04-03"
    },
    {
      "rebalance_date": "2026-04-02",
      "rank": 69,
      "symbol": "300823",
      "name": "建科智能",
      "market_cap": 2076076222.9499998,
      "target_weight": 0.01,
      "signal_date": "2026-04-02",
      "effective_date": "2026-04-03"
    },
    {
      "rebalance_date": "2026-04-02",
      "rank": 70,
      "symbol": "301024",
      "name": "霍普股份",
      "market_cap": 2076686099.9999998,
      "target_weight": 0.01,
      "signal_date": "2026-04-02",
      "effective_date": "2026-04-03"
    },
    {
      "rebalance_date": "2026-04-02",
      "rank": 71,
      "symbol": "688058",
      "name": "宝兰德",
      "market_cap": 2080954767.3600001,
      "target_weight": 0.01,
      "signal_date": "2026-04-02",
      "effective_date": "2026-04-03"
    },
    {
      "rebalance_date": "2026-04-02",
      "rank": 72,
      "symbol": "300717",
      "name": "华信新材",
      "market_cap": 2081193750.0,
      "target_weight": 0.01,
      "signal_date": "2026-04-02",
      "effective_date": "2026-04-03"
    },
    {
      "rebalance_date": "2026-04-02",
      "rank": 73,
      "symbol": "301273",
      "name": "瑞晨环保",
      "market_cap": 2083343311.3599997,
      "target_weight": 0.01,
      "signal_date": "2026-04-02",
      "effective_date": "2026-04-03"
    },
    {
      "rebalance_date": "2026-04-02",
      "rank": 74,
      "symbol": "300556",
      "name": "丝路视觉",
      "market_cap": 2086060771.08,
      "target_weight": 0.01,
      "signal_date": "2026-04-02",
      "effective_date": "2026-04-03"
    },
    {
      "rebalance_date": "2026-04-02",
      "rank": 75,
      "symbol": "688420",
      "name": "美腾科技",
      "market_cap": 2086948000.0000002,
      "target_weight": 0.01,
      "signal_date": "2026-04-02",
      "effective_date": "2026-04-03"
    },
    {
      "rebalance_date": "2026-04-02",
      "rank": 76,
      "symbol": "688466",
      "name": "金科环境",
      "market_cap": 2090057540.7199998,
      "target_weight": 0.01,
      "signal_date": "2026-04-02",
      "effective_date": "2026-04-03"
    },
    {
      "rebalance_date": "2026-04-02",
      "rank": 77,
      "symbol": "600137",
      "name": "浪莎股份",
      "market_cap": 2090178142.0,
      "target_weight": 0.01,
      "signal_date": "2026-04-02",
      "effective_date": "2026-04-03"
    },
    {
      "rebalance_date": "2026-04-02",
      "rank": 78,
      "symbol": "300886",
      "name": "华业香料",
      "market_cap": 2095091980.0,
      "target_weight": 0.01,
      "signal_date": "2026-04-02",
      "effective_date": "2026-04-03"
    },
    {
      "rebalance_date": "2026-04-02",
      "rank": 79,
      "symbol": "603709",
      "name": "中源家居",
      "market_cap": 2095403064.0,
      "target_weight": 0.01,
      "signal_date": "2026-04-02",
      "effective_date": "2026-04-03"
    },
    {
      "rebalance_date": "2026-04-02",
      "rank": 80,
      "symbol": "603860",
      "name": "中公高科",
      "market_cap": 2099753199.9999998,
      "target_weight": 0.01,
      "signal_date": "2026-04-02",
      "effective_date": "2026-04-03"
    },
    {
      "rebalance_date": "2026-04-02",
      "rank": 81,
      "symbol": "002910",
      "name": "庄园牧场",
      "market_cap": 2104003373.72,
      "target_weight": 0.01,
      "signal_date": "2026-04-02",
      "effective_date": "2026-04-03"
    },
    {
      "rebalance_date": "2026-04-02",
      "rank": 82,
      "symbol": "603908",
      "name": "牧高笛",
      "market_cap": 2104669928.8,
      "target_weight": 0.01,
      "signal_date": "2026-04-02",
      "effective_date": "2026-04-03"
    },
    {
      "rebalance_date": "2026-04-02",
      "rank": 83,
      "symbol": "301030",
      "name": "仕净科技",
      "market_cap": 2108834298.5999997,
      "target_weight": 0.01,
      "signal_date": "2026-04-02",
      "effective_date": "2026-04-03"
    },
    {
      "rebalance_date": "2026-04-02",
      "rank": 84,
      "symbol": "688638",
      "name": "誉辰智能",
      "market_cap": 2111200000.0000002,
      "target_weight": 0.01,
      "signal_date": "2026-04-02",
      "effective_date": "2026-04-03"
    },
    {
      "rebalance_date": "2026-04-02",
      "rank": 85,
      "symbol": "301139",
      "name": "元道通信",
      "market_cap": 2115505919.9999998,
      "target_weight": 0.01,
      "signal_date": "2026-04-02",
      "effective_date": "2026-04-03"
    },
    {
      "rebalance_date": "2026-04-02",
      "rank": 86,
      "symbol": "300013",
      "name": "新宁物流",
      "market_cap": 2116180208.26,
      "target_weight": 0.01,
      "signal_date": "2026-04-02",
      "effective_date": "2026-04-03"
    },
    {
      "rebalance_date": "2026-04-02",
      "rank": 87,
      "symbol": "002316",
      "name": "亚联发展",
      "market_cap": 2122848000.0000002,
      "target_weight": 0.01,
      "signal_date": "2026-04-02",
      "effective_date": "2026-04-03"
    },
    {
      "rebalance_date": "2026-04-02",
      "rank": 88,
      "symbol": "300923",
      "name": "研奥股份",
      "market_cap": 2138706000.0,
      "target_weight": 0.01,
      "signal_date": "2026-04-02",
      "effective_date": "2026-04-03"
    },
    {
      "rebalance_date": "2026-04-02",
      "rank": 89,
      "symbol": "002963",
      "name": "豪尔赛",
      "market_cap": 2153154197.6000004,
      "target_weight": 0.01,
      "signal_date": "2026-04-02",
      "effective_date": "2026-04-03"
    },
    {
      "rebalance_date": "2026-04-02",
      "rank": 90,
      "symbol": "300163",
      "name": "先锋新材",
      "market_cap": 2161439999.9999995,
      "target_weight": 0.01,
      "signal_date": "2026-04-02",
      "effective_date": "2026-04-03"
    },
    {
      "rebalance_date": "2026-04-02",
      "rank": 91,
      "symbol": "605567",
      "name": "春雪食品",
      "market_cap": 2168000000.0,
      "target_weight": 0.01,
      "signal_date": "2026-04-02",
      "effective_date": "2026-04-03"
    },
    {
      "rebalance_date": "2026-04-02",
      "rank": 92,
      "symbol": "300675",
      "name": "建科院",
      "market_cap": 2169200493.0,
      "target_weight": 0.01,
      "signal_date": "2026-04-02",
      "effective_date": "2026-04-03"
    },
    {
      "rebalance_date": "2026-04-02",
      "rank": 93,
      "symbol": "002820",
      "name": "桂发祥",
      "market_cap": 2169377586.0,
      "target_weight": 0.01,
      "signal_date": "2026-04-02",
      "effective_date": "2026-04-03"
    },
    {
      "rebalance_date": "2026-04-02",
      "rank": 94,
      "symbol": "688395",
      "name": "正弦电气",
      "market_cap": 2174468749.2,
      "target_weight": 0.01,
      "signal_date": "2026-04-02",
      "effective_date": "2026-04-03"
    },
    {
      "rebalance_date": "2026-04-02",
      "rank": 95,
      "symbol": "300334",
      "name": "津膜科技",
      "market_cap": 2177891216.7599998,
      "target_weight": 0.01,
      "signal_date": "2026-04-02",
      "effective_date": "2026-04-03"
    },
    {
      "rebalance_date": "2026-04-02",
      "rank": 96,
      "symbol": "600303",
      "name": "曙光股份",
      "market_cap": 2180697433.09,
      "target_weight": 0.01,
      "signal_date": "2026-04-02",
      "effective_date": "2026-04-03"
    },
    {
      "rebalance_date": "2026-04-02",
      "rank": 97,
      "symbol": "688670",
      "name": "金迪克",
      "market_cap": 2181872000.0,
      "target_weight": 0.01,
      "signal_date": "2026-04-02",
      "effective_date": "2026-04-03"
    },
    {
      "rebalance_date": "2026-04-02",
      "rank": 98,
      "symbol": "300640",
      "name": "德艺文创",
      "market_cap": 2189393726.08,
      "target_weight": 0.01,
      "signal_date": "2026-04-02",
      "effective_date": "2026-04-03"
    },
    {
      "rebalance_date": "2026-04-02",
      "rank": 99,
      "symbol": "600119",
      "name": "长江投资",
      "market_cap": 2191622220.0,
      "target_weight": 0.01,
      "signal_date": "2026-04-02",
      "effective_date": "2026-04-03"
    },
    {
      "rebalance_date": "2026-04-02",
      "rank": 100,
      "symbol": "001366",
      "name": "播恩集团",
      "market_cap": 2194888800.0,
      "target_weight": 0.01,
      "signal_date": "2026-04-02",
      "effective_date": "2026-04-03"
    }
  ],
  "effective_members": [
    {
      "rebalance_date": "2026-04-02",
      "rank": 1,
      "symbol": "688701",
      "name": "卓锦股份",
      "market_cap": 1220581311.48,
      "target_weight": 0.01
    },
    {
      "rebalance_date": "2026-04-02",
      "rank": 2,
      "symbol": "688296",
      "name": "和达科技",
      "market_cap": 1462026843.0,
      "target_weight": 0.01
    },
    {
      "rebalance_date": "2026-04-02",
      "rank": 3,
      "symbol": "002193",
      "name": "如意集团",
      "market_cap": 1481310013.0,
      "target_weight": 0.01
    },
    {
      "rebalance_date": "2026-04-02",
      "rank": 4,
      "symbol": "002856",
      "name": "美芝股份",
      "market_cap": 1481675247.6,
      "target_weight": 0.01
    },
    {
      "rebalance_date": "2026-04-02",
      "rank": 5,
      "symbol": "002883",
      "name": "中设股份",
      "market_cap": 1481931505.3400002,
      "target_weight": 0.01
    },
    {
      "rebalance_date": "2026-04-02",
      "rank": 6,
      "symbol": "002719",
      "name": "麦趣尔",
      "market_cap": 1483668173.6399999,
      "target_weight": 0.01
    },
    {
      "rebalance_date": "2026-04-02",
      "rank": 7,
      "symbol": "688659",
      "name": "元琛科技",
      "market_cap": 1534400000.0,
      "target_weight": 0.01
    },
    {
      "rebalance_date": "2026-04-02",
      "rank": 8,
      "symbol": "301098",
      "name": "金埔园林",
      "market_cap": 1535862084.65,
      "target_weight": 0.01
    },
    {
      "rebalance_date": "2026-04-02",
      "rank": 9,
      "symbol": "600543",
      "name": "莫高股份",
      "market_cap": 1538164800.0,
      "target_weight": 0.01
    },
    {
      "rebalance_date": "2026-04-02",
      "rank": 10,
      "symbol": "603729",
      "name": "龙韵股份",
      "market_cap": 1568078400.0,
      "target_weight": 0.01
    },
    {
      "rebalance_date": "2026-04-02",
      "rank": 11,
      "symbol": "688217",
      "name": "睿昂基因",
      "market_cap": 1571784913.44,
      "target_weight": 0.01
    },
    {
      "rebalance_date": "2026-04-02",
      "rank": 12,
      "symbol": "600455",
      "name": "博通股份",
      "market_cap": 1618286780.0000002,
      "target_weight": 0.01
    },
    {
      "rebalance_date": "2026-04-02",
      "rank": 13,
      "symbol": "300417",
      "name": "南华仪器",
      "market_cap": 1637634144.0,
      "target_weight": 0.01
    },
    {
      "rebalance_date": "2026-04-02",
      "rank": 14,
      "symbol": "300929",
      "name": "华骐环保",
      "market_cap": 1643733972.64,
      "target_weight": 0.01
    },
    {
      "rebalance_date": "2026-04-02",
      "rank": 15,
      "symbol": "300665",
      "name": "飞鹿股份",
      "market_cap": 1646471889.6,
      "target_weight": 0.01
    },
    {
      "rebalance_date": "2026-04-02",
      "rank": 16,
      "symbol": "300621",
      "name": "维业股份",
      "market_cap": 1666534166.9999998,
      "target_weight": 0.01
    },
    {
      "rebalance_date": "2026-04-02",
      "rank": 17,
      "symbol": "688671",
      "name": "碧兴物联",
      "market_cap": 1678734082.0,
      "target_weight": 0.01
    },
    {
      "rebalance_date": "2026-04-02",
      "rank": 18,
      "symbol": "688004",
      "name": "博汇科技",
      "market_cap": 1709077920.0000002,
      "target_weight": 0.01
    },
    {
      "rebalance_date": "2026-04-02",
      "rank": 19,
      "symbol": "600476",
      "name": "湘邮科技",
      "market_cap": 1720227600.0,
      "target_weight": 0.01
    },
    {
      "rebalance_date": "2026-04-02",
      "rank": 20,
      "symbol": "688078",
      "name": "龙软科技",
      "market_cap": 1755263439.9999998,
      "target_weight": 0.01
    },
    {
      "rebalance_date": "2026-04-02",
      "rank": 21,
      "symbol": "300405",
      "name": "科隆股份",
      "market_cap": 1763110560.2000003,
      "target_weight": 0.01
    },
    {
      "rebalance_date": "2026-04-02",
      "rank": 22,
      "symbol": "301372",
      "name": "科净源",
      "market_cap": 1788342894.3999999,
      "target_weight": 0.01
    },
    {
      "rebalance_date": "2026-04-02",
      "rank": 23,
      "symbol": "688528",
      "name": "秦川物联",
      "market_cap": 1795920000.0,
      "target_weight": 0.01
    },
    {
      "rebalance_date": "2026-04-02",
      "rank": 24,
      "symbol": "688067",
      "name": "爱威科技",
      "market_cap": 1801320000.0,
      "target_weight": 0.01
    },
    {
      "rebalance_date": "2026-04-02",
      "rank": 25,
      "symbol": "300295",
      "name": "三六五网",
      "market_cap": 1812707105.8400002,
      "target_weight": 0.01
    },
    {
      "rebalance_date": "2026-04-02",
      "rank": 26,
      "symbol": "301167",
      "name": "建研设计",
      "market_cap": 1818879999.9999998,
      "target_weight": 0.01
    },
    {
      "rebalance_date": "2026-04-02",
      "rank": 27,
      "symbol": "300500",
      "name": "启迪设计",
      "market_cap": 1837174616.64,
      "target_weight": 0.01
    },
    {
      "rebalance_date": "2026-04-02",
      "rank": 28,
      "symbol": "600561",
      "name": "江西长运",
      "market_cap": 1849099200.0000002,
      "target_weight": 0.01
    },
    {
      "rebalance_date": "2026-04-02",
      "rank": 29,
      "symbol": "688573",
      "name": "信宇人",
      "market_cap": 1851468108.72,
      "target_weight": 0.01
    },
    {
      "rebalance_date": "2026-04-02",
      "rank": 30,
      "symbol": "688329",
      "name": "艾隆科技",
      "market_cap": 1853572000.0,
      "target_weight": 0.01
    },
    {
      "rebalance_date": "2026-04-02",
      "rank": 31,
      "symbol": "300649",
      "name": "杭州园林",
      "market_cap": 1863101688.6300004,
      "target_weight": 0.01
    },
    {
      "rebalance_date": "2026-04-02",
      "rank": 32,
      "symbol": "688021",
      "name": "奥福科技",
      "market_cap": 1872136066.5,
      "target_weight": 0.01
    },
    {
      "rebalance_date": "2026-04-02",
      "rank": 33,
      "symbol": "600697",
      "name": "欧亚集团",
      "market_cap": 1894738973.25,
      "target_weight": 0.01
    },
    {
      "rebalance_date": "2026-04-02",
      "rank": 34,
      "symbol": "688681",
      "name": "科汇股份",
      "market_cap": 1898713800.0,
      "target_weight": 0.01
    },
    {
      "rebalance_date": "2026-04-02",
      "rank": 35,
      "symbol": "600883",
      "name": "博闻科技",
      "market_cap": 1905230160.0,
      "target_weight": 0.01
    },
    {
      "rebalance_date": "2026-04-02",
      "rank": 36,
      "symbol": "688096",
      "name": "京源环保",
      "market_cap": 1907238784.32,
      "target_weight": 0.01
    },
    {
      "rebalance_date": "2026-04-02",
      "rank": 37,
      "symbol": "300635",
      "name": "中达安",
      "market_cap": 1913991380.0,
      "target_weight": 0.01
    },
    {
      "rebalance_date": "2026-04-02",
      "rank": 38,
      "symbol": "688565",
      "name": "力源科技",
      "market_cap": 1927025099.9999998,
      "target_weight": 0.01
    },
    {
      "rebalance_date": "2026-04-02",
      "rank": 39,
      "symbol": "600847",
      "name": "万里股份",
      "market_cap": 1929888365.9999998,
      "target_weight": 0.01
    },
    {
      "rebalance_date": "2026-04-02",
      "rank": 40,
      "symbol": "300169",
      "name": "天晟新材",
      "market_cap": 1936346979.6000001,
      "target_weight": 0.01
    },
    {
      "rebalance_date": "2026-04-02",
      "rank": 41,
      "symbol": "300670",
      "name": "大烨智能",
      "market_cap": 1945891741.06,
      "target_weight": 0.01
    },
    {
      "rebalance_date": "2026-04-02",
      "rank": 42,
      "symbol": "603717",
      "name": "天域生物",
      "market_cap": 1946881270.3999999,
      "target_weight": 0.01
    },
    {
      "rebalance_date": "2026-04-02",
      "rank": 43,
      "symbol": "002494",
      "name": "华斯股份",
      "market_cap": 1958242626.42,
      "target_weight": 0.01
    },
    {
      "rebalance_date": "2026-04-02",
      "rank": 44,
      "symbol": "001211",
      "name": "双枪科技",
      "market_cap": 1958400000.0,
      "target_weight": 0.01
    },
    {
      "rebalance_date": "2026-04-02",
      "rank": 45,
      "symbol": "600778",
      "name": "友好集团",
      "market_cap": 1959280604.0800002,
      "target_weight": 0.01
    },
    {
      "rebalance_date": "2026-04-02",
      "rank": 46,
      "symbol": "603880",
      "name": "南卫股份",
      "market_cap": 1965485600.0,
      "target_weight": 0.01
    },
    {
      "rebalance_date": "2026-04-02",
      "rank": 47,
      "symbol": "603879",
      "name": "永悦科技",
      "market_cap": 1965614086.8000002,
      "target_weight": 0.01
    },
    {
      "rebalance_date": "2026-04-02",
      "rank": 48,
      "symbol": "688793",
      "name": "倍轻松",
      "market_cap": 1981901362.1399999,
      "target_weight": 0.01
    },
    {
      "rebalance_date": "2026-04-02",
      "rank": 49,
      "symbol": "002715",
      "name": "登云股份",
      "market_cap": 1992720000.0,
      "target_weight": 0.01
    },
    {
      "rebalance_date": "2026-04-02",
      "rank": 50,
      "symbol": "600493",
      "name": "凤竹纺织",
      "market_cap": 1993760000.0,
      "target_weight": 0.01
    },
    {
      "rebalance_date": "2026-04-02",
      "rank": 51,
      "symbol": "301336",
      "name": "趣睡科技",
      "market_cap": 2008400000.0,
      "target_weight": 0.01
    },
    {
      "rebalance_date": "2026-04-02",
      "rank": 52,
      "symbol": "301037",
      "name": "保立佳",
      "market_cap": 2009007862.7,
      "target_weight": 0.01
    },
    {
      "rebalance_date": "2026-04-02",
      "rank": 53,
      "symbol": "000610",
      "name": "西安旅游",
      "market_cap": 2024194553.5500002,
      "target_weight": 0.01
    },
    {
      "rebalance_date": "2026-04-02",
      "rank": 54,
      "symbol": "300838",
      "name": "浙江力诺",
      "market_cap": 2025517040.0,
      "target_weight": 0.01
    },
    {
      "rebalance_date": "2026-04-02",
      "rank": 55,
      "symbol": "300535",
      "name": "达威股份",
      "market_cap": 2030166801.11,
      "target_weight": 0.01
    },
    {
      "rebalance_date": "2026-04-02",
      "rank": 56,
      "symbol": "300958",
      "name": "建工修复",
      "market_cap": 2032873429.63,
      "target_weight": 0.01
    },
    {
      "rebalance_date": "2026-04-02",
      "rank": 57,
      "symbol": "301049",
      "name": "超越科技",
      "market_cap": 2033044414.3799999,
      "target_weight": 0.01
    },
    {
      "rebalance_date": "2026-04-02",
      "rank": 58,
      "symbol": "603022",
      "name": "新通联",
      "market_cap": 2038000000.0,
      "target_weight": 0.01
    },
    {
      "rebalance_date": "2026-04-02",
      "rank": 59,
      "symbol": "688193",
      "name": "仁度生物",
      "market_cap": 2041159177.8,
      "target_weight": 0.01
    },
    {
      "rebalance_date": "2026-04-02",
      "rank": 60,
      "symbol": "603779",
      "name": "威龙股份",
      "market_cap": 2042308937.1000001,
      "target_weight": 0.01
    },
    {
      "rebalance_date": "2026-04-02",
      "rank": 61,
      "symbol": "002591",
      "name": "恒大高新",
      "market_cap": 2044358486.04,
      "target_weight": 0.01
    },
    {
      "rebalance_date": "2026-04-02",
      "rank": 62,
      "symbol": "688695",
      "name": "中创股份",
      "market_cap": 2045485640.9000003,
      "target_weight": 0.01
    },
    {
      "rebalance_date": "2026-04-02",
      "rank": 63,
      "symbol": "600448",
      "name": "华纺股份",
      "market_cap": 2053212098.12,
      "target_weight": 0.01
    },
    {
      "rebalance_date": "2026-04-02",
      "rank": 64,
      "symbol": "002188",
      "name": "中天服务",
      "market_cap": 2054212265.9199998,
      "target_weight": 0.01
    },
    {
      "rebalance_date": "2026-04-02",
      "rank": 65,
      "symbol": "001336",
      "name": "楚环科技",
      "market_cap": 2055150395.0000002,
      "target_weight": 0.01
    },
    {
      "rebalance_date": "2026-04-02",
      "rank": 66,
      "symbol": "300220",
      "name": "金运激光",
      "market_cap": 2068416000.0,
      "target_weight": 0.01
    },
    {
      "rebalance_date": "2026-04-02",
      "rank": 67,
      "symbol": "300614",
      "name": "百川畅银",
      "market_cap": 2069684759.1000001,
      "target_weight": 0.01
    },
    {
      "rebalance_date": "2026-04-02",
      "rank": 68,
      "symbol": "300106",
      "name": "西部牧业",
      "market_cap": 2071056638.0,
      "target_weight": 0.01
    },
    {
      "rebalance_date": "2026-04-02",
      "rank": 69,
      "symbol": "300823",
      "name": "建科智能",
      "market_cap": 2076076222.9499998,
      "target_weight": 0.01
    },
    {
      "rebalance_date": "2026-04-02",
      "rank": 70,
      "symbol": "301024",
      "name": "霍普股份",
      "market_cap": 2076686099.9999998,
      "target_weight": 0.01
    },
    {
      "rebalance_date": "2026-04-02",
      "rank": 71,
      "symbol": "688058",
      "name": "宝兰德",
      "market_cap": 2080954767.3600001,
      "target_weight": 0.01
    },
    {
      "rebalance_date": "2026-04-02",
      "rank": 72,
      "symbol": "300717",
      "name": "华信新材",
      "market_cap": 2081193750.0,
      "target_weight": 0.01
    },
    {
      "rebalance_date": "2026-04-02",
      "rank": 73,
      "symbol": "301273",
      "name": "瑞晨环保",
      "market_cap": 2083343311.3599997,
      "target_weight": 0.01
    },
    {
      "rebalance_date": "2026-04-02",
      "rank": 74,
      "symbol": "300556",
      "name": "丝路视觉",
      "market_cap": 2086060771.08,
      "target_weight": 0.01
    },
    {
      "rebalance_date": "2026-04-02",
      "rank": 75,
      "symbol": "688420",
      "name": "美腾科技",
      "market_cap": 2086948000.0000002,
      "target_weight": 0.01
    },
    {
      "rebalance_date": "2026-04-02",
      "rank": 76,
      "symbol": "688466",
      "name": "金科环境",
      "market_cap": 2090057540.7199998,
      "target_weight": 0.01
    },
    {
      "rebalance_date": "2026-04-02",
      "rank": 77,
      "symbol": "600137",
      "name": "浪莎股份",
      "market_cap": 2090178142.0,
      "target_weight": 0.01
    },
    {
      "rebalance_date": "2026-04-02",
      "rank": 78,
      "symbol": "300886",
      "name": "华业香料",
      "market_cap": 2095091980.0,
      "target_weight": 0.01
    },
    {
      "rebalance_date": "2026-04-02",
      "rank": 79,
      "symbol": "603709",
      "name": "中源家居",
      "market_cap": 2095403064.0,
      "target_weight": 0.01
    },
    {
      "rebalance_date": "2026-04-02",
      "rank": 80,
      "symbol": "603860",
      "name": "中公高科",
      "market_cap": 2099753199.9999998,
      "target_weight": 0.01
    },
    {
      "rebalance_date": "2026-04-02",
      "rank": 81,
      "symbol": "002910",
      "name": "庄园牧场",
      "market_cap": 2104003373.72,
      "target_weight": 0.01
    },
    {
      "rebalance_date": "2026-04-02",
      "rank": 82,
      "symbol": "603908",
      "name": "牧高笛",
      "market_cap": 2104669928.8,
      "target_weight": 0.01
    },
    {
      "rebalance_date": "2026-04-02",
      "rank": 83,
      "symbol": "301030",
      "name": "仕净科技",
      "market_cap": 2108834298.5999997,
      "target_weight": 0.01
    },
    {
      "rebalance_date": "2026-04-02",
      "rank": 84,
      "symbol": "688638",
      "name": "誉辰智能",
      "market_cap": 2111200000.0000002,
      "target_weight": 0.01
    },
    {
      "rebalance_date": "2026-04-02",
      "rank": 85,
      "symbol": "301139",
      "name": "元道通信",
      "market_cap": 2115505919.9999998,
      "target_weight": 0.01
    },
    {
      "rebalance_date": "2026-04-02",
      "rank": 86,
      "symbol": "300013",
      "name": "新宁物流",
      "market_cap": 2116180208.26,
      "target_weight": 0.01
    },
    {
      "rebalance_date": "2026-04-02",
      "rank": 87,
      "symbol": "002316",
      "name": "亚联发展",
      "market_cap": 2122848000.0000002,
      "target_weight": 0.01
    },
    {
      "rebalance_date": "2026-04-02",
      "rank": 88,
      "symbol": "300923",
      "name": "研奥股份",
      "market_cap": 2138706000.0,
      "target_weight": 0.01
    },
    {
      "rebalance_date": "2026-04-02",
      "rank": 89,
      "symbol": "002963",
      "name": "豪尔赛",
      "market_cap": 2153154197.6000004,
      "target_weight": 0.01
    },
    {
      "rebalance_date": "2026-04-02",
      "rank": 90,
      "symbol": "300163",
      "name": "先锋新材",
      "market_cap": 2161439999.9999995,
      "target_weight": 0.01
    },
    {
      "rebalance_date": "2026-04-02",
      "rank": 91,
      "symbol": "605567",
      "name": "春雪食品",
      "market_cap": 2168000000.0,
      "target_weight": 0.01
    },
    {
      "rebalance_date": "2026-04-02",
      "rank": 92,
      "symbol": "300675",
      "name": "建科院",
      "market_cap": 2169200493.0,
      "target_weight": 0.01
    },
    {
      "rebalance_date": "2026-04-02",
      "rank": 93,
      "symbol": "002820",
      "name": "桂发祥",
      "market_cap": 2169377586.0,
      "target_weight": 0.01
    },
    {
      "rebalance_date": "2026-04-02",
      "rank": 94,
      "symbol": "688395",
      "name": "正弦电气",
      "market_cap": 2174468749.2,
      "target_weight": 0.01
    },
    {
      "rebalance_date": "2026-04-02",
      "rank": 95,
      "symbol": "300334",
      "name": "津膜科技",
      "market_cap": 2177891216.7599998,
      "target_weight": 0.01
    },
    {
      "rebalance_date": "2026-04-02",
      "rank": 96,
      "symbol": "600303",
      "name": "曙光股份",
      "market_cap": 2180697433.09,
      "target_weight": 0.01
    },
    {
      "rebalance_date": "2026-04-02",
      "rank": 97,
      "symbol": "688670",
      "name": "金迪克",
      "market_cap": 2181872000.0,
      "target_weight": 0.01
    },
    {
      "rebalance_date": "2026-04-02",
      "rank": 98,
      "symbol": "300640",
      "name": "德艺文创",
      "market_cap": 2189393726.08,
      "target_weight": 0.01
    },
    {
      "rebalance_date": "2026-04-02",
      "rank": 99,
      "symbol": "600119",
      "name": "长江投资",
      "market_cap": 2191622220.0,
      "target_weight": 0.01
    },
    {
      "rebalance_date": "2026-04-02",
      "rank": 100,
      "symbol": "001366",
      "name": "播恩集团",
      "market_cap": 2194888800.0,
      "target_weight": 0.01
    }
  ],
  "changes_df": [
    {
      "action": "enter",
      "symbol": "688021",
      "name": "奥福科技",
      "prev_rank": NaN,
      "new_rank": 32.0,
      "signal_date": "2026-04-02",
      "effective_date": "2026-04-03"
    },
    {
      "action": "enter",
      "symbol": "300614",
      "name": "百川畅银",
      "prev_rank": NaN,
      "new_rank": 67.0,
      "signal_date": "2026-04-02",
      "effective_date": "2026-04-03"
    },
    {
      "action": "enter",
      "symbol": "301024",
      "name": "霍普股份",
      "prev_rank": NaN,
      "new_rank": 70.0,
      "signal_date": "2026-04-02",
      "effective_date": "2026-04-03"
    },
    {
      "action": "enter",
      "symbol": "300556",
      "name": "丝路视觉",
      "prev_rank": NaN,
      "new_rank": 74.0,
      "signal_date": "2026-04-02",
      "effective_date": "2026-04-03"
    },
    {
      "action": "enter",
      "symbol": "301030",
      "name": "仕净科技",
      "prev_rank": NaN,
      "new_rank": 83.0,
      "signal_date": "2026-04-02",
      "effective_date": "2026-04-03"
    },
    {
      "action": "enter",
      "symbol": "002963",
      "name": "豪尔赛",
      "prev_rank": NaN,
      "new_rank": 89.0,
      "signal_date": "2026-04-02",
      "effective_date": "2026-04-03"
    },
    {
      "action": "enter",
      "symbol": "300675",
      "name": "建科院",
      "prev_rank": NaN,
      "new_rank": 92.0,
      "signal_date": "2026-04-02",
      "effective_date": "2026-04-03"
    },
    {
      "action": "enter",
      "symbol": "688395",
      "name": "正弦电气",
      "prev_rank": NaN,
      "new_rank": 94.0,
      "signal_date": "2026-04-02",
      "effective_date": "2026-04-03"
    },
    {
      "action": "enter",
      "symbol": "300334",
      "name": "津膜科技",
      "prev_rank": NaN,
      "new_rank": 95.0,
      "signal_date": "2026-04-02",
      "effective_date": "2026-04-03"
    },
    {
      "action": "enter",
      "symbol": "300640",
      "name": "德艺文创",
      "prev_rank": NaN,
      "new_rank": 98.0,
      "signal_date": "2026-04-02",
      "effective_date": "2026-04-03"
    },
    {
      "action": "exit",
      "symbol": "688156",
      "name": "路德科技",
      "prev_rank": 49.0,
      "new_rank": NaN,
      "signal_date": "2026-04-02",
      "effective_date": "2026-04-03"
    },
    {
      "action": "exit",
      "symbol": "688189",
      "name": "南新制药",
      "prev_rank": 50.0,
      "new_rank": NaN,
      "signal_date": "2026-04-02",
      "effective_date": "2026-04-03"
    },
    {
      "action": "exit",
      "symbol": "300069",
      "name": "金利华电",
      "prev_rank": 55.0,
      "new_rank": NaN,
      "signal_date": "2026-04-02",
      "effective_date": "2026-04-03"
    },
    {
      "action": "exit",
      "symbol": "688450",
      "name": "光格科技",
      "prev_rank": 63.0,
      "new_rank": NaN,
      "signal_date": "2026-04-02",
      "effective_date": "2026-04-03"
    },
    {
      "action": "exit",
      "symbol": "000632",
      "name": "三木集团",
      "prev_rank": 80.0,
      "new_rank": NaN,
      "signal_date": "2026-04-02",
      "effective_date": "2026-04-03"
    },
    {
      "action": "exit",
      "symbol": "000692",
      "name": "惠天热电",
      "prev_rank": 84.0,
      "new_rank": NaN,
      "signal_date": "2026-04-02",
      "effective_date": "2026-04-03"
    },
    {
      "action": "exit",
      "symbol": "688178",
      "name": "万德斯",
      "prev_rank": 91.0,
      "new_rank": NaN,
      "signal_date": "2026-04-02",
      "effective_date": "2026-04-03"
    },
    {
      "action": "exit",
      "symbol": "600768",
      "name": "宁波富邦",
      "prev_rank": 95.0,
      "new_rank": NaN,
      "signal_date": "2026-04-02",
      "effective_date": "2026-04-03"
    },
    {
      "action": "exit",
      "symbol": "603214",
      "name": "爱婴室",
      "prev_rank": 98.0,
      "new_rank": NaN,
      "signal_date": "2026-04-02",
      "effective_date": "2026-04-03"
    },
    {
      "action": "exit",
      "symbol": "600149",
      "name": "廊坊发展",
      "prev_rank": 100.0,
      "new_rank": NaN,
      "signal_date": "2026-04-02",
      "effective_date": "2026-04-03"
    }
  ],
  "latest_rebalance": "2026-04-02",
  "prev_rebalance": "2026-03-19",
  "next_rebalance": null,
  "effective_rebalance": "2026-04-02",
  "rebalance_effective_date": "2026-04-03",
  "freshness": {
    "status": "正常",
    "latest_trade_date": "2026-04-10",
    "current_date": "2026-04-11",
    "stale_calendar_days": 1
  },
  "rebuild_meta": {
    "strategy_version": "1.1",
    "strategy_label": "v1.1（主线版，0.8x 对冲）",
    "fixed_hedge_ratio": 0.8,
    "last_trade_signal_date": null,
    "last_trade_signal_action": null,
    "candidate_pool": 600,
    "history_symbols_ok": 600,
    "history_symbols_failed": 0,
    "rebalance_count": 3,
    "effective_member_count": 100,
    "stage_attempts": [
      500,
      600
    ],
    "window_trade_days": 24,
    "strict_validated": true,
    "validated_exact_pools": [
      500,
      600
    ],
    "signal_consensus": true
  }
}