[
  {
    "date": "2026-03-05",
    "open": 10.3,
    "close_raw": 10.4,
    "high": 10.69,
    "low": 10.3
  },
  {
    "date": "2026-03-06",
    "open": 10.32,
    "close_raw": 10.81,
    "high": 10.81,
    "low": 10.32
  },
  {
    "date": "2026-03-09",
    "open": 10.57,
    "close_raw": 10.65,
    "high": 10.76,
    "low": 10.4
  },
  {
    "date": "2026-03-10",
    "open": 10.75,
    "close_raw": 11.09,
    "high": 11.16,
    "low": 10.74
  },
  {
    "date": "2026-03-11",
    "open": 11.06,
    "close_raw": 10.94,
    "high": 11.23,
    "low": 10.91
  },
  {
    "date": "2026-03-12",
    "open": 10.99,
    "close_raw": 10.86,
    "high": 11.08,
    "low": 10.79
  },
  {
    "date": "2026-03-13",
    "open": 10.9,
    "close_raw": 10.79,
    "high": 11.06,
    "low": 10.76
  },
  {
    "date": "2026-03-16",
    "open": 10.73,
    "close_raw": 10.77,
    "high": 10.91,
    "low": 10.59
  },
  {
    "date": "2026-03-17",
    "open": 10.79,
    "close_raw": 10.43,
    "high": 10.88,
    "low": 10.43
  },
  {
    "date": "2026-03-18",
    "open": 10.5,
    "close_raw": 10.65,
    "high": 10.66,
    "low": 10.31
  },
  {
    "date": "2026-03-19",
    "open": 10.56,
    "close_raw": 10.27,
    "high": 10.64,
    "low": 10.21
  },
  {
    "date": "2026-03-20",
    "open": 10.3,
    "close_raw": 9.71,
    "high": 10.38,
    "low": 9.65
  },
  {
    "date": "2026-03-23",
    "open": 9.58,
    "close_raw": 8.97,
    "high": 9.69,
    "low": 8.74
  },
  {
    "date": "2026-03-24",
    "open": 9.3,
    "close_raw": 9.63,
    "high": 9.65,
    "low": 8.92
  },
  {
    "date": "2026-03-25",
    "open": 9.67,
    "close_raw": 9.88,
    "high": 9.97,
    "low": 9.63
  },
  {
    "date": "2026-03-26",
    "open": 9.84,
    "close_raw": 9.68,
    "high": 9.98,
    "low": 9.52
  },
  {
    "date": "2026-03-27",
    "open": 9.5,
    "close_raw": 9.9,
    "high": 9.95,
    "low": 9.45
  },
  {
    "date": "2026-03-30",
    "open": 9.84,
    "close_raw": 9.85,
    "high": 9.92,
    "low": 9.65
  },
  {
    "date": "2026-03-31",
    "open": 9.93,
    "close_raw": 9.7,
    "high": 10.08,
    "low": 9.61
  },
  {
    "date": "2026-04-01",
    "open": 9.91,
    "close_raw": 9.79,
    "high": 9.98,
    "low": 9.73
  },
  {
    "date": "2026-04-02",
    "open": 9.85,
    "close_raw": 9.59,
    "high": 9.92,
    "low": 9.45
  },
  {
    "date": "2026-04-03",
    "open": 9.65,
    "close_raw": 9.15,
    "high": 9.65,
    "low": 9.04
  },
  {
    "date": "2026-04-07",
    "open": 9.15,
    "close_raw": 9.54,
    "high": 9.55,
    "low": 9.01
  },
  {
    "date": "2026-04-08",
    "open": 9.81,
    "close_raw": 10.03,
    "high": 10.04,
    "low": 9.72
  },
  {
    "date": "2026-04-09",
    "open": 10.06,
    "close_raw": 9.68,
    "high": 10.06,
    "low": 9.68
  }
]