[
  {
    "date": "2026-03-12",
    "close_raw": 29.69
  },
  {
    "date": "2026-03-13",
    "close_raw": 26.92
  },
  {
    "date": "2026-03-16",
    "close_raw": 27.0
  },
  {
    "date": "2026-03-17",
    "close_raw": 25.95
  },
  {
    "date": "2026-03-18",
    "close_raw": 29.04
  },
  {
    "date": "2026-03-19",
    "close_raw": 29.09
  },
  {
    "date": "2026-03-20",
    "close_raw": 27.61
  },
  {
    "date": "2026-03-23",
    "close_raw": 28.18
  },
  {
    "date": "2026-03-24",
    "close_raw": 29.19
  },
  {
    "date": "2026-03-25",
    "close_raw": 29.39
  },
  {
    "date": "2026-03-26",
    "close_raw": 28.42
  },
  {
    "date": "2026-03-27",
    "close_raw": 27.84
  },
  {
    "date": "2026-03-30",
    "close_raw": 27.71
  },
  {
    "date": "2026-03-31",
    "close_raw": 26.43
  },
  {
    "date": "2026-04-01",
    "close_raw": 28.55
  },
  {
    "date": "2026-04-02",
    "close_raw": 26.62
  },
  {
    "date": "2026-04-03",
    "close_raw": 26.66
  },
  {
    "date": "2026-04-07",
    "close_raw": 25.25
  },
  {
    "date": "2026-04-08",
    "close_raw": 28.59
  }
]